getanime/__init__.py
getanime/getanime.py
getanime-1.2.0.dist-info/LICENSE.txt
getanime-1.2.0.dist-info/METADATA
getanime-1.2.0.dist-info/WHEEL
getanime-1.2.0.dist-info/top_level.txt
getanime-1.2.0.dist-info/RECORD
